sanelogging/__init__.py
sanelogging-1.1.0.dist-info/LICENSE
sanelogging-1.1.0.dist-info/METADATA
sanelogging-1.1.0.dist-info/WHEEL
sanelogging-1.1.0.dist-info/top_level.txt
sanelogging-1.1.0.dist-info/RECORD
